aliyunstoreplugin/__init__.py
aliyunstoreplugin/store/__init__.py
aliyunstoreplugin/store/artifact/__init__.py
aliyunstoreplugin/store/artifact/aliyun_oss_artifact_repo.py
aliyunstoreplugin-1.0.0.dist-info/METADATA
aliyunstoreplugin-1.0.0.dist-info/WHEEL
aliyunstoreplugin-1.0.0.dist-info/entry_points.txt
aliyunstoreplugin-1.0.0.dist-info/top_level.txt
aliyunstoreplugin-1.0.0.dist-info/RECORD
