Metadata-Version: 2.1
Name: aliyunstoreplugin
Version: 1.0.0
Summary: Plugin that provides Aliyun oss Artifact Store functionality for MLflow
Home-page: https://github.com/SeaOfOcean/mlflow-aliyunstore
Author: Xianyan Jia
Author-email: jiaxianyan@gmail.com
License: UNKNOWN
Platform: UNKNOWN
Requires-Dist: mlflow
Requires-Dist: oss2
